nfl_data_py/__init__.py
nfl_data_py-0.3.3.dist-info/LICENSE
nfl_data_py-0.3.3.dist-info/METADATA
nfl_data_py-0.3.3.dist-info/WHEEL
nfl_data_py-0.3.3.dist-info/top_level.txt
nfl_data_py-0.3.3.dist-info/RECORD
