Metadata-Version: 2.1
Name: nfl_data_py
Version: 0.3.3
Summary: python library for interacting with NFL data sourced from nflfastR
Home-page: https://github.com/nflverse/nfl_data_py
Author: Alec Ostrander
Author-email: alec.ostrander@gmail.com
License: MIT
Classifier: License :: OSI Approved :: MIT License
Classifier: Programming Language :: Python
Classifier: Programming Language :: Python :: 3
Classifier: Programming Language :: Python :: 3 :: Only
Classifier: Programming Language :: Python :: 3.6
Classifier: Programming Language :: Python :: 3.7
Classifier: Programming Language :: Python :: 3.8
Classifier: Programming Language :: Python :: 3.9
Classifier: Programming Language :: Python :: 3.10
Classifier: Programming Language :: Python :: 3.11
Classifier: Programming Language :: Python :: 3.12
Classifier: Programming Language :: Python :: Implementation :: CPython
Classifier: Programming Language :: Python :: Implementation :: PyPy
Classifier: Intended Audience :: Developers
Classifier: Intended Audience :: Science/Research
Classifier: Topic :: Scientific/Engineering :: Information Analysis
Classifier: Operating System :: OS Independent
Requires-Python: >=3.6.0
License-File: LICENSE
Requires-Dist: numpy<2.0,>=1.0
Requires-Dist: pandas<2.0,>=1.0
Requires-Dist: appdirs>1
Requires-Dist: fastparquet>0.5
